MANIFEST.in
README.md
setup.py
fardel_ecommerce/__init__.py
fardel_ecommerce/panel.py
fardel_ecommerce/views.py
fardel_ecommerce.egg-info/PKG-INFO
fardel_ecommerce.egg-info/SOURCES.txt
fardel_ecommerce.egg-info/dependency_links.txt
fardel_ecommerce.egg-info/requires.txt
fardel_ecommerce.egg-info/top_level.txt
fardel_ecommerce/checkout/__init__.py
fardel_ecommerce/checkout/models.py
fardel_ecommerce/checkout/panel.py
fardel_ecommerce/checkout/views.py
fardel_ecommerce/discount/__init__.py
fardel_ecommerce/discount/utils.py
fardel_ecommerce/media/templates/order/orders_info.html
fardel_ecommerce/media/templates/order/orders_list.html
fardel_ecommerce/media/templates/payment/payments_list.html
fardel_ecommerce/media/templates/product/categories_form.html
fardel_ecommerce/media/templates/product/categories_info.html
fardel_ecommerce/media/templates/product/categories_list.html
fardel_ecommerce/media/templates/product/products_attributes_add_value_form.html
fardel_ecommerce/media/templates/product/products_attributes_form.html
fardel_ecommerce/media/templates/product/products_attributes_info.html
fardel_ecommerce/media/templates/product/products_attributes_list.html
fardel_ecommerce/media/templates/product/products_form.html
fardel_ecommerce/media/templates/product/products_images.html
fardel_ecommerce/media/templates/product/products_info.html
fardel_ecommerce/media/templates/product/products_list.html
fardel_ecommerce/media/templates/product/products_types_form.html
fardel_ecommerce/media/templates/product/products_types_list.html
fardel_ecommerce/media/templates/product/variants_form.html
fardel_ecommerce/order/__init__.py
fardel_ecommerce/order/models.py
fardel_ecommerce/order/panel.py
fardel_ecommerce/order/views.py
fardel_ecommerce/product/__init__.py
fardel_ecommerce/product/models.py
fardel_ecommerce/product/panel.py
fardel_ecommerce/product/views.py